mlops_api_gemstack/__init__.py
mlops_api_gemstack/api.py
mlops_api_gemstack/record_rosbag.py
mlops_api_gemstack-0.4.1.dist-info/LICENSE
mlops_api_gemstack-0.4.1.dist-info/METADATA
mlops_api_gemstack-0.4.1.dist-info/WHEEL
mlops_api_gemstack-0.4.1.dist-info/entry_points.txt
mlops_api_gemstack-0.4.1.dist-info/top_level.txt
mlops_api_gemstack-0.4.1.dist-info/RECORD
